<?xml version="1.0" encoding="utf-8" ?>
<dwsync>
<file name="smiley-cry.gif" server="166.62.27.176/public_html/" local="131155094435805473" remote="131167077000000000" Dst="2" />
<file name="smiley-cool.gif" server="166.62.27.176/public_html/" local="131155094385390432" remote="131167077000000000" Dst="2" />
<file name="smiley-embarassed.gif" server="166.62.27.176/public_html/" local="131155094486220514" remote="131167077000000000" Dst="2" />
<file name="smiley-foot-in-mouth.gif" server="166.62.27.176/public_html/" local="131155094535185410" remote="131167077000000000" Dst="2" />
<file name="smiley-innocent.gif" server="166.62.27.176/public_html/" local="131155094634415332" remote="131167077000000000" Dst="2" />
<file name="smiley-frown.gif" server="166.62.27.176/public_html/" local="131155094585580449" remote="131167077000000000" Dst="2" />
<file name="smiley-kiss.gif" server="166.62.27.176/public_html/" local="131155094681660056" remote="131167077000000000" Dst="2" />
<file name="smiley-money-mouth.gif" server="166.62.27.176/public_html/" local="131155094782510140" remote="131167077000000000" Dst="2" />
<file name="smiley-sealed.gif" server="166.62.27.176/public_html/" local="131155094825124401" remote="131167077000000000" Dst="2" />
<file name="smiley-laughing.gif" server="166.62.27.176/public_html/" local="131155094732085098" remote="131167077000000000" Dst="2" />
<file name="smiley-surprised.gif" server="166.62.27.176/public_html/" local="131155094906942582" remote="131167077000000000" Dst="2" />
<file name="smiley-tongue-out.gif" server="166.62.27.176/public_html/" local="131155094950986986" remote="131167077000000000" Dst="2" />
<file name="smiley-smile.gif" server="166.62.27.176/public_html/" local="131155094867608649" remote="131167077000000000" Dst="2" />
<file name="smiley-wink.gif" server="166.62.27.176/public_html/" local="131155095034295316" remote="131167077000000000" Dst="2" />
<file name="smiley-yell.gif" server="166.62.27.176/public_html/" local="131155095081610047" remote="131167077000000000" Dst="2" />
<file name="smiley-undecided.gif" server="166.62.27.176/public_html/" local="131155094991841071" remote="131167077000000000" Dst="2" />
</dwsync>